<?xml version="1.0" encoding="utf-8"?>
<System>
  <P Name="Location">[23, 14, 1017, 767]</P>
  <P Name="SystemRect">[0.000000, 0.000000, 0.000000, 0.000000]</P>
  <P Name="SetExecutionDomain">off</P>
  <P Name="ExecutionDomainType">Deduce</P>
  <P Name="SimulinkSubDomain">Simulink</P>
  <Block BlockType="Inport" Name="In1" SID="4">
    <P Name="Position">[-40, 28, -10, 42]</P>
    <P Name="ZOrder">3</P>
    <Port>
      <P Name="PortNumber">1</P>
      <P Name="Name">i dot</P>
    </Port>
  </Block>
  <Block BlockType="Inport" Name="In2" SID="5">
    <P Name="Position">[-40, 103, -10, 117]</P>
    <P Name="ZOrder">4</P>
    <P Name="Port">2</P>
    <Port>
      <P Name="PortNumber">1</P>
      <P Name="Name">angular
acceleration</P>
    </Port>
  </Block>
  <Block BlockType="Integrator" Name="Integrator" SID="1">
    <P Name="Ports">[1, 1]</P>
    <P Name="Position">[70, 20, 100, 50]</P>
    <P Name="ZOrder">1</P>
    <Port>
      <P Name="PortNumber">1</P>
      <P Name="Name">current</P>
    </Port>
  </Block>
  <Block BlockType="Integrator" Name="Integrator1" SID="2">
    <P Name="Ports">[1, 1]</P>
    <P Name="Position">[70, 95, 100, 125]</P>
    <P Name="ZOrder">2</P>
    <Port>
      <P Name="PortNumber">1</P>
      <P Name="Name">angular
velocity</P>
    </Port>
  </Block>
  <Block BlockType="Outport" Name="Out1" SID="6">
    <P Name="Position">[180, 28, 210, 42]</P>
    <P Name="ZOrder">5</P>
  </Block>
  <Block BlockType="Outport" Name="Out2" SID="7">
    <P Name="Position">[180, 103, 210, 117]</P>
    <P Name="ZOrder">6</P>
    <P Name="Port">2</P>
  </Block>
  <Line>
    <P Name="Name">i dot</P>
    <P Name="ZOrder">6</P>
    <P Name="Labels">[1, 1]</P>
    <P Name="Src">4#out:1</P>
    <P Name="Dst">1#in:1</P>
  </Line>
  <Line>
    <P Name="Name">angular
acceleration</P>
    <P Name="ZOrder">7</P>
    <P Name="Labels">[1, 1]</P>
    <P Name="Src">5#out:1</P>
    <P Name="Dst">2#in:1</P>
  </Line>
  <Line>
    <P Name="Name">current</P>
    <P Name="ZOrder">8</P>
    <P Name="Labels">[1, 1]</P>
    <P Name="Src">1#out:1</P>
    <P Name="Dst">6#in:1</P>
  </Line>
  <Line>
    <P Name="Name">angular
velocity</P>
    <P Name="ZOrder">9</P>
    <P Name="Labels">[1, 1]</P>
    <P Name="Src">2#out:1</P>
    <P Name="Dst">7#in:1</P>
  </Line>
</System>
